acgs2_core/__init__.py
acgs2_core/hash.py
acgs2_core/policy.py
acgs2_core/result.py
acgs2_core/validator.py
acgs2_core-0.1.0.dist-info/licenses/LICENSE
examples/basic_usage.py
examples/llm_integration.py
tests/__init__.py
tests/test_pattern_protection.py
tests/test_validator.py
acgs2_core-0.1.0.dist-info/METADATA
acgs2_core-0.1.0.dist-info/WHEEL
acgs2_core-0.1.0.dist-info/top_level.txt
acgs2_core-0.1.0.dist-info/RECORD
