Metadata-Version: 2.4
Name: acgs2-core
Version: 0.1.0
Summary: Cryptographic AI compliance verification in one line of code. Zero dependencies.
Author-email: Soln AI <dev@soln.ai>
Maintainer-email: Soln AI <dev@soln.ai>
License: MIT
Project-URL: Homepage, https://github.com/solnai/acgs2-core
Project-URL: Documentation, https://soln.ai/docs
Project-URL: Repository, https://github.com/solnai/acgs2-core
Project-URL: Issues, https://github.com/solnai/acgs2-core/issues
Project-URL: Changelog, https://github.com/solnai/acgs2-core/releases
Keywords: ai,compliance,governance,verification,cryptographic,audit,constitutional,llm,safety
Classifier: Development Status :: 4 - Beta
Classifier: Intended Audience :: Developers
Classifier: License :: OSI Approved :: MIT License
Classifier: Operating System :: OS Independent
Classifier: Programming Language :: Python :: 3
Classifier: Programming Language :: Python :: 3.9
Classifier: Programming Language :: Python :: 3.10
Classifier: Programming Language :: Python :: 3.11
Classifier: Programming Language :: Python :: 3.12
Classifier: Programming Language :: Python :: 3.13
Classifier: Topic :: Scientific/Engineering :: Artificial Intelligence
Classifier: Topic :: Security :: Cryptography
Classifier: Typing :: Typed
Requires-Python: >=3.9
License-File: LICENSE
Provides-Extra: dev
Requires-Dist: pytest>=7.0.0; extra == "dev"
Requires-Dist: pytest-cov>=4.0.0; extra == "dev"
Requires-Dist: black>=23.0.0; extra == "dev"
Requires-Dist: ruff>=0.1.0; extra == "dev"
Requires-Dist: mypy>=1.0.0; extra == "dev"
Dynamic: license-file
